snyk_tags/__init__.py
snyk_tags/__main__.py
snyk_tags/attribute.py
snyk_tags/collection.py
snyk_tags/component.py
snyk_tags/files.py
snyk_tags/github.py
snyk_tags/lib/__init__.py
snyk_tags/lib/api.py
snyk_tags/lib/component/rules/__init__.py
snyk_tags/lib/component/rules/matcher.py
snyk_tags/lib/component/rules/model.py
snyk_tags/list.py
snyk_tags/remove.py
snyk_tags/tag.py
snyk_tags/tags.py
snyk_tags-2.5.3.dist-info/LICENSE.md
snyk_tags-2.5.3.dist-info/METADATA
snyk_tags-2.5.3.dist-info/WHEEL
snyk_tags-2.5.3.dist-info/entry_points.txt
snyk_tags-2.5.3.dist-info/RECORD
