Metadata-Version: 2.3
Name: snyk-tags
Version: 2.5.3
Summary: CLI tool designed to manage tags and attributes at scale
License: MIT
Keywords: snyk
Author: EricFernandezSnyk
Author-email: eric.fernandez@snyk.io
Requires-Python: >=3.8,<4.0
Classifier: License :: OSI Approved :: MIT License
Classifier: Programming Language :: Python :: 3
Classifier: Programming Language :: Python :: 3.8
Classifier: Programming Language :: Python :: 3.9
Classifier: Programming Language :: Python :: 3.10
Classifier: Programming Language :: Python :: 3.11
Classifier: Programming Language :: Python :: 3.12
Classifier: Programming Language :: Python :: 3.13
Requires-Dist: PyGithub (>=2.3,<3.0)
Requires-Dist: backoff (>=2.2.1,<3.0.0)
Requires-Dist: certifi (==2023.7.22)
Requires-Dist: colorama (>=0.4.5,<0.5.0)
Requires-Dist: httpx (>=0.24.0,<0.25.0)
Requires-Dist: jsonschema (>=4,<5)
Requires-Dist: pygments (==2.15.0)
Requires-Dist: pysnyk (>=0.9.19,<0.10.0)
Requires-Dist: pyyaml (>=6.0.1,<7.0.0)
Requires-Dist: requests (==2.31.0)
Requires-Dist: rich (>=10.11.0)
Requires-Dist: shellingham (>=1.4.0,<2.0.0)
Requires-Dist: typer (>=0.5.0)
Requires-Dist: validators (>=0.28.1,<0.29.0)
Project-URL: Repository, https://github.com/snyk-labs/snyk-tags-tool
